fritzprofiles/__init__.py
fritzprofiles/fritzprofiles.py
fritzprofiles-0.7.3.data/scripts/fritzprofiles
fritzprofiles-0.7.3.dist-info/LICENSE.md
fritzprofiles-0.7.3.dist-info/METADATA
fritzprofiles-0.7.3.dist-info/WHEEL
fritzprofiles-0.7.3.dist-info/top_level.txt
fritzprofiles-0.7.3.dist-info/RECORD
