Metadata-Version: 2.1
Name: fritzprofiles
Version: 0.7.3
Summary: A tool to switch the online time of profiles in the AVM Fritz!Box
Home-page: https://github.com/AaronDavidSchneider/fritzprofiles
Author: Aaron David Schneider
Author-email: aaron.david.schneider@gmail.com
License: UNKNOWN
Platform: UNKNOWN
Classifier: Programming Language :: Python :: 3
Classifier: License :: OSI Approved :: MIT License
Classifier: Operating System :: OS Independent
Requires-Dist: requests
Requires-Dist: lxml
